iipyper/__init__.py
iipyper/audio.py
iipyper/midi.py
iipyper/osc.py
iipyper/state.py
iipyper/timing.py
iipyper/tui.py
iipyper/types.py
iipyper/util.py
iipyper-0.4.0.dist-info/LICENSE
iipyper-0.4.0.dist-info/METADATA
iipyper-0.4.0.dist-info/WHEEL
iipyper-0.4.0.dist-info/RECORD
