Metadata-Version: 2.1
Name: iipyper
Version: 0.4.0
Summary: A Python package for rapid prototyping with MIDI and OSC
Home-page: https://github.com/Intelligent-Instruments-Lab/iipyper
License: MIT
Author: Victor Shepardson
Author-email: victor.shepardson@gmail.com
Requires-Python: >=3.10,<3.14
Classifier: License :: OSI Approved :: MIT License
Classifier: Programming Language :: Python :: 3
Classifier: Programming Language :: Python :: 3.10
Classifier: Programming Language :: Python :: 3.11
Classifier: Programming Language :: Python :: 3.12
Requires-Dist: cffi (>=1.17.1)
Requires-Dist: fire (>=0.6.0,<0.8.0)
Requires-Dist: mido (>=1.3.0,<2.0.0)
Requires-Dist: pydantic (>=2.5.2,<3.0.0)
Requires-Dist: pydantic-numpy (>=8.0.0,<9.0.0)
Requires-Dist: python-osc (>=1.8.3,<2.0.0)
Requires-Dist: python-rtmidi (>=1.5.7,<2.0.0)
Requires-Dist: sounddevice (>=0.4.6,<0.5.0)
Requires-Dist: textual (>=2.0.0,<3.0.0)
Project-URL: Documentation, https://intelligent-instruments-lab.github.io/iipyper/
Project-URL: Repository, https://github.com/Intelligent-Instruments-Lab/iipyper
